regional_mom6/MOM_parameter_tools.py
regional_mom6/__init__.py
regional_mom6/_version.py
regional_mom6/config.py
regional_mom6/regional_mom6.py
regional_mom6/regridding.py
regional_mom6/rotation.py
regional_mom6/utils.py
regional_mom6/demos/premade_run_directories/README.md
regional_mom6/demos/premade_run_directories/common_files/MOM_input
regional_mom6/demos/premade_run_directories/common_files/MOM_layout
regional_mom6/demos/premade_run_directories/common_files/MOM_override
regional_mom6/demos/premade_run_directories/common_files/SIS_input
regional_mom6/demos/premade_run_directories/common_files/config.yaml
regional_mom6/demos/premade_run_directories/common_files/data_table
regional_mom6/demos/premade_run_directories/common_files/diag_table
regional_mom6/demos/premade_run_directories/common_files/field_table
regional_mom6/demos/premade_run_directories/common_files/input.nml
regional_mom6/demos/premade_run_directories/era5_surface/data_table
regional_mom6/demos/premade_run_directories/era5_surface/input.nml
regional_mom6/demos/premade_run_directories/jra_surface/config.yaml
regional_mom6/demos/premade_run_directories/jra_surface/data_table
regional_mom6-1.0.1.dist-info/licenses/LICENSE
regional_mom6-1.0.1.dist-info/METADATA
regional_mom6-1.0.1.dist-info/WHEEL
regional_mom6-1.0.1.dist-info/top_level.txt
regional_mom6-1.0.1.dist-info/RECORD
